gregtech/__init__.py
gregtech/__main__.py
gregtech/flow/__init__.py
gregtech/flow/cli.py
gregtech/flow/exceptions.py
gregtech/flow/graph/__init__.py
gregtech/flow/graph/_back_edges.py
gregtech/flow/graph/_output.py
gregtech/flow/graph/_port_nodes.py
gregtech/flow/graph/_post_processing.py
gregtech/flow/graph/_pre_processing.py
gregtech/flow/graph/_solver.py
gregtech/flow/graph/_utils.py
gregtech/flow/gtnh/__init__.py
gregtech/flow/gtnh/overclocks.py
gregtech/flow/recipe/__init__.py
gregtech/flow/recipe/basic_types.py
gregtech/flow/recipe/load_project.py
gregtech/flow/resources/config_schema.json
gregtech/flow/resources/config_template.yaml
gregtech/flow/resources/data.yaml
gregtech/flow/resources/header_schema.json
gregtech/flow/resources/project_schema.json
gregtech/flow/schemas.py
gregtech/flow/wrapper.py
gregtech_flow-1.0.0.dist-info/METADATA
gregtech_flow-1.0.0.dist-info/entry_points.txt
gregtech_flow-1.0.0.dist-info/WHEEL
gregtech_flow-1.0.0.dist-info/LICENSE.txt
gregtech_flow-1.0.0.dist-info/RECORD
