Metadata-Version: 2.1
Name: gregtech-flow
Version: 1.0.0
Summary: YAML Driven Flowcharts for Gregtech: New Horizons
Home-page: https://velolib.github.io/gregtech-flow
License: MIT
Keywords: gregtech,minecraft,graphviz,graphs
Author: velolib
Author-email: vlocitize@gmail.com
Requires-Python: >=3.11,<4.0
Classifier: Development Status :: 5 - Production/Stable
Classifier: Environment :: Console
Classifier: Intended Audience :: End Users/Desktop
Classifier: License :: OSI Approved :: MIT License
Classifier: Natural Language :: English
Classifier: Operating System :: Microsoft :: Windows
Classifier: Operating System :: POSIX :: Linux
Classifier: Programming Language :: Python :: 3
Classifier: Programming Language :: Python :: 3.11
Requires-Dist: fastjsonschema (>=2.16.2,<3.0.0)
Requires-Dist: graphviz (>=0.20.1,<0.21.0)
Requires-Dist: prompt-toolkit (>=3.0.36,<4.0.0)
Requires-Dist: rich (>=13.0.0,<14.0.0)
Requires-Dist: ruamel-yaml (>=0.17.21,<0.18.0)
Requires-Dist: sympy (>=1.11.1,<2.0.0)
Requires-Dist: typer (>=0.7.0,<0.8.0)
Project-URL: Documentation, https://velolib.github.io/gregtech-flow
Project-URL: Repository, https://github.com/velolib/gregtech-flow
